strands_utcp/__init__.py
strands_utcp/py.typed
strands_utcp/utcp_tool_adapter.py
strands_utcp-0.1.1.dist-info/METADATA
strands_utcp-0.1.1.dist-info/WHEEL
strands_utcp-0.1.1.dist-info/licenses/LICENSE
strands_utcp-0.1.1.dist-info/RECORD
