Metadata-Version: 2.4
Name: strands-utcp
Version: 0.1.1
Summary: Universal Tool Calling Protocol (UTCP) integration for Strands Agents SDK
Project-URL: Homepage, https://github.com/universal-tool-calling-protocol/strands-utcp
Project-URL: Documentation, https://github.com/universal-tool-calling-protocol/strands-utcp#readme
Project-URL: Repository, https://github.com/universal-tool-calling-protocol/strands-utcp
Project-URL: Issues, https://github.com/universal-tool-calling-protocol/strands-utcp/issues
Author-email: UTCP Community <community@utcp.dev>
License-Expression: MIT
License-File: LICENSE
Keywords: agents,ai,llm,strands,tools,utcp
Classifier: Development Status :: 3 - Alpha
Classifier: Intended Audience :: Developers
Classifier: License :: OSI Approved :: MIT License
Classifier: Programming Language :: Python :: 3
Classifier: Programming Language :: Python :: 3.10
Classifier: Programming Language :: Python :: 3.11
Classifier: Programming Language :: Python :: 3.12
Classifier: Topic :: Scientific/Engineering :: Artificial Intelligence
Classifier: Topic :: Software Development :: Libraries :: Python Modules
Requires-Python: >=3.10
Requires-Dist: httpx>=0.27.0
Requires-Dist: pydantic>=2.0.0
Requires-Dist: strands-agents
Requires-Dist: utcp-http>=1.0.0
Requires-Dist: utcp>=1.0.0
Provides-Extra: dev
Requires-Dist: black>=23.0.0; extra == 'dev'
Requires-Dist: build; extra == 'dev'
Requires-Dist: mypy>=1.0.0; extra == 'dev'
Requires-Dist: pytest-asyncio>=0.21.0; extra == 'dev'
Requires-Dist: pytest-cov>=4.0.0; extra == 'dev'
Requires-Dist: pytest-mock>=3.0.0; extra == 'dev'
Requires-Dist: pytest>=7.0.0; extra == 'dev'
Requires-Dist: ruff>=0.1.0; extra == 'dev'
Requires-Dist: twine; extra == 'dev'
